datamallet/__init__.py
datamallet/tabular/__init__.py
datamallet/tabular/feature.py
datamallet/tabular/imputation.py
datamallet/tabular/preprocess.py
datamallet/tabular/timeseries.py
datamallet/tabular/utils.py
datamallet/visualization/__init__.py
datamallet/visualization/autoplot.py
datamallet/visualization/plot.py
datamallet/visualization/utils.py
datamallet-0.22.0.dist-info/LICENSE
datamallet-0.22.0.dist-info/METADATA
datamallet-0.22.0.dist-info/WHEEL
datamallet-0.22.0.dist-info/top_level.txt
datamallet-0.22.0.dist-info/RECORD
