Metadata-Version: 2.1
Name: datamallet
Version: 0.22.0
Summary: Helper tools for the data science workflow
Home-page: UNKNOWN
Author: Olabode Alamu
Author-email: 
License: MIT
Platform: UNKNOWN
Classifier: Intended Audience :: Developers
Classifier: License :: OSI Approved :: MIT License
Classifier: Programming Language :: Python
Classifier: Programming Language :: Python :: 3
Classifier: Programming Language :: Python :: 3.6
Classifier: Programming Language :: Python :: 3.7
Classifier: Programming Language :: Python :: 3.8
Classifier: Programming Language :: Python :: 3.9
Classifier: Operating System :: OS Independent
License-File: LICENSE
Requires-Dist: pandas (>=1.1.5)
Requires-Dist: scikit-learn (>=0.24.2)
Requires-Dist: numpy (>=1.19.5)
Requires-Dist: scipy (==1.5.4)
Requires-Dist: plotly (>=5.3.1)
